fifteen_ai/__init__.py
fifteen_ai/__main__.py
fifteen_ai-0.2.2.dist-info/LICENSE
fifteen_ai-0.2.2.dist-info/WHEEL
fifteen_ai-0.2.2.dist-info/METADATA
fifteen_ai-0.2.2.dist-info/RECORD
